datetimejp/__init__.py
datetimejp/__version__.py
datetimejp/common.py
datetimejp/jdate.py
datetimejp/jdatetime.py
datetimejp-1.1.0.dist-info/METADATA
datetimejp-1.1.0.dist-info/WHEEL
datetimejp-1.1.0.dist-info/top_level.txt
datetimejp-1.1.0.dist-info/RECORD
