Metadata-Version: 2.1
Name: datetimejp
Version: 1.1.0
Summary: A datetime extension module that supports Japanese era dates
Author: Solla Umiyama
Author-email: usolla-tech@yahoo.co.jp
License: MIT
Keywords: Japanese era,datetimejp,datetime
Classifier: Development Status :: 4 - Beta
Classifier: Intended Audience :: Developers
Classifier: License :: OSI Approved :: MIT License
Classifier: Topic :: Software Development :: Libraries
Classifier: Topic :: Software Development :: Localization
Classifier: Topic :: Utilities
Classifier: Programming Language :: Python :: 3
